mcp_atlassian_kw/__init__.py
mcp_atlassian_kw/exceptions.py
mcp_atlassian_kw/confluence/__init__.py
mcp_atlassian_kw/confluence/client.py
mcp_atlassian_kw/confluence/comments.py
mcp_atlassian_kw/confluence/config.py
mcp_atlassian_kw/confluence/constants.py
mcp_atlassian_kw/confluence/labels.py
mcp_atlassian_kw/confluence/pages.py
mcp_atlassian_kw/confluence/search.py
mcp_atlassian_kw/confluence/spaces.py
mcp_atlassian_kw/confluence/users.py
mcp_atlassian_kw/confluence/utils.py
mcp_atlassian_kw/confluence/v2_adapter.py
mcp_atlassian_kw/jira/__init__.py
mcp_atlassian_kw/jira/attachments.py
mcp_atlassian_kw/jira/boards.py
mcp_atlassian_kw/jira/client.py
mcp_atlassian_kw/jira/comments.py
mcp_atlassian_kw/jira/config.py
mcp_atlassian_kw/jira/constants.py
mcp_atlassian_kw/jira/epics.py
mcp_atlassian_kw/jira/fields.py
mcp_atlassian_kw/jira/formatting.py
mcp_atlassian_kw/jira/issues.py
mcp_atlassian_kw/jira/links.py
mcp_atlassian_kw/jira/projects.py
mcp_atlassian_kw/jira/protocols.py
mcp_atlassian_kw/jira/search.py
mcp_atlassian_kw/jira/sprints.py
mcp_atlassian_kw/jira/transitions.py
mcp_atlassian_kw/jira/users.py
mcp_atlassian_kw/jira/worklog.py
mcp_atlassian_kw/models/__init__.py
mcp_atlassian_kw/models/base.py
mcp_atlassian_kw/models/constants.py
mcp_atlassian_kw/models/confluence/__init__.py
mcp_atlassian_kw/models/confluence/comment.py
mcp_atlassian_kw/models/confluence/common.py
mcp_atlassian_kw/models/confluence/label.py
mcp_atlassian_kw/models/confluence/page.py
mcp_atlassian_kw/models/confluence/search.py
mcp_atlassian_kw/models/confluence/space.py
mcp_atlassian_kw/models/confluence/user_search.py
mcp_atlassian_kw/models/jira/__init__.py
mcp_atlassian_kw/models/jira/agile.py
mcp_atlassian_kw/models/jira/comment.py
mcp_atlassian_kw/models/jira/common.py
mcp_atlassian_kw/models/jira/issue.py
mcp_atlassian_kw/models/jira/link.py
mcp_atlassian_kw/models/jira/project.py
mcp_atlassian_kw/models/jira/search.py
mcp_atlassian_kw/models/jira/version.py
mcp_atlassian_kw-0.11.10.dist-info/METADATA
mcp_atlassian_kw-0.11.10.dist-info/WHEEL
mcp_atlassian_kw-0.11.10.dist-info/entry_points.txt
mcp_atlassian_kw-0.11.10.dist-info/licenses/LICENSE
mcp_atlassian_kw-0.11.10.dist-info/RECORD
